torch_complex/__init__.py
torch_complex/functional.py
torch_complex/tensor.py
torch_complex/utils.py
torch_complex-0.4.4.dist-info/METADATA
torch_complex-0.4.4.dist-info/WHEEL
torch_complex-0.4.4.dist-info/top_level.txt
torch_complex-0.4.4.dist-info/RECORD
