Metadata-Version: 2.1
Name: torch_complex
Version: 0.4.4
Summary: A fugacious python class for PyTorch-ComplexTensor
Home-page: https://github.com/kamo-naoyuki/torch_complex
Author: Naoyuki Kamo
Author-email: naoyuki.kamo829@gmail.com
License: UNKNOWN
Platform: UNKNOWN
Classifier: Programming Language :: Python
Classifier: Programming Language :: Python :: 3
Classifier: Programming Language :: Python :: 3.6
Classifier: Programming Language :: Python :: 3.7
Classifier: Programming Language :: Python :: 3.8
Classifier: Development Status :: 5 - Production/Stable
Classifier: Intended Audience :: Science/Research
Classifier: Operating System :: POSIX :: Linux
Classifier: License :: OSI Approved :: Apache Software License
Classifier: Topic :: Software Development :: Libraries :: Python Modules
